dexec/__init__.py
dexec/__main__.py
dexec-0.1.2.dist-info/LICENSE
dexec-0.1.2.dist-info/METADATA
dexec-0.1.2.dist-info/WHEEL
dexec-0.1.2.dist-info/entry_points.txt
dexec-0.1.2.dist-info/top_level.txt
dexec-0.1.2.dist-info/RECORD
