Metadata-Version: 2.1
Name: dexec
Version: 0.1.2
Summary: Easily run commands inside your projects' Docker containers
Home-page: https://github.com/apeschar/dexec
Author: Albert Peschar
Author-email: albert@peschar.net
License: UNKNOWN
Project-URL: Bug Tracker, https://github.com/apeschar/dexec/issues
Platform: UNKNOWN
Classifier: Programming Language :: Python :: 3
Classifier: License :: OSI Approved :: GNU General Public License v3 (GPLv3)
Classifier: Operating System :: OS Independent
Requires-Python: >=3.6
